x_ae_a_12/__init__.py
x_ae_a_12/console.py
x_ae_a_12/wikipedia.py
x_ae_a_12-0.2.1.dist-info/entry_points.txt
x_ae_a_12-0.2.1.dist-info/LICENSE
x_ae_a_12-0.2.1.dist-info/WHEEL
x_ae_a_12-0.2.1.dist-info/METADATA
x_ae_a_12-0.2.1.dist-info/RECORD
