Metadata-Version: 2.1
Name: x-ae-a-12
Version: 0.2.1
Summary: The X-AE-A-12 Python project
Home-page: https://github.com/SpencerOfwiti/X-AE-A-12
License: MIT
Keywords: X-AE-A-12,X AE A-12,x-ae-a-12,x ae a-12
Author: Spencer Ofwiti
Author-email: maxspencer56@gmail.com
Requires-Python: >=3.7,<4.0
Classifier: License :: OSI Approved :: MIT License
Classifier: Programming Language :: Python :: 3
Classifier: Programming Language :: Python :: 3.7
Classifier: Programming Language :: Python :: 3.8
Requires-Dist: click (>=7.1.2,<8.0.0)
Requires-Dist: desert (>=2020.1.6,<2021.0.0)
Requires-Dist: importlib_metadata (>=1.6.0,<2.0.0); python_version < "3.8"
Requires-Dist: marshmallow (>=3.6.0,<4.0.0)
Requires-Dist: pytest-mock (>=3.1.0,<4.0.0)
Requires-Dist: requests (>=2.23.0,<3.0.0)
Project-URL: Documentation, https://x-ae-a-12.readthedocs.io
Project-URL: Repository, https://github.com/SpencerOfwiti/X-AE-A-12
